joshbasiccalculator/__init__.py
eyad-0.0.1.dist-info/LICENCE.txt
eyad-0.0.1.dist-info/METADATA
eyad-0.0.1.dist-info/WHEEL
eyad-0.0.1.dist-info/top_level.txt
eyad-0.0.1.dist-info/RECORD
