Metadata-Version: 2.1
Name: eyad
Version: 0.0.1
Summary: very code for eyad
Home-page: UNKNOWN
Author: eyad
Author-email: hashemshaiban@gmail.com
License: MIT
Keywords: eyad
Platform: UNKNOWN
Classifier: Development Status :: 5 - Production/Stable
Classifier: Intended Audience :: Education
Classifier: Operating System :: Microsoft :: Windows :: Windows 10
Classifier: License :: OSI Approved :: MIT License
Classifier: Programming Language :: Python :: 3
License-File: LICENCE.txt
